{
  "pagina": "32 van 112",
  "type": "content",
  "hoofdstuk": "Waarom zijn audits belangrijk?",
  "transcriptie": "Waarom zijn audits belangrijk?\n\nAudit\nSystematisch, 'onafhankelijk' en gedocumenteerd proces voor het verkrijgen van audit-bewijzen (bv.: relevante records, feitelijke verklaringen of andere informatie die relevant zijn en te bepalen in hoeverre aan de auditcriteria voldoen (ISO 19011 paragraaf 3.1)\n\nEnkele van de fundamentele redenen voor het uitvoeren van interne audits van informatiebeveiliging smanagementsystemen zijn:\n\nErvoor zorgen dat de eisen wordt voldaan, d.w.z. ervoor zorgen dat wat er moet gebeuren ook daadwerkelijk kan gebeuren.\n\nAfwikkingsdoelen van het ISMS begrijpen. Hoe goed bereikt het ISMS de beoogde doelstellingen?\n\nErvoor zorgen dat er toereikende en volledige documentatie word bijgehouden om talening en de effectiviteit van het systeem aan te tonen.\n\nBeslissingen zullen genomen worden op basis van auditresultaten.\n\nObjectieve feiten aan het management verstrekken. (Alle conclusies van de audit moeten met feitelijke gegevens ondersteund kunnen worden; gebaseerd voor verbeterring identificeren.\n\nZowel sterkte als zwakte punte bepaaldrukken.\nGebaseerd voor verbetering identificeren.\n\nHet laatste punt is erg belangrijk.",
  "kernconcepten": [
    "Audit definitie ISO 19011",
    "Onafhankelijk proces",
    "Auditbewijzen",
    "Interne audits ISMS",
    "Naleving van eisen",
    "Doelstellingen ISMS",
    "Documentatie bijhouden",
    "Objectieve feiten",
    "Verbeteringen identificeren",
    "Sterkte en zwakte punten"
  ],
  "_source": "Foto 18-04-2026, 18 38 28.jpg",
  "_input_tokens": 1897,
  "_output_tokens": 524
}