{
  "pagina": "onbekend",
  "type": "content",
  "hoofdstuk": "Falten",
  "transcriptie": "Falten\n\nIedere organisatie heeft behoette aan vooruitwende verwdering. Organisaties kunnen daarvoör PDC^A\nverschillende modellen gebruiken. zoals: TQM, Kaizen, DMAIC en PDCA.\n\nHet Demingwiele, PDCA-model is een conceptuele illustratie van het in ISO 27001 gehanteerde PDCA-\nprocessmodel. Het model geeft de processen niet op een gedetailleerd niveau weer (uitsluitend op gemeenk\nniveau), maar geeft de norm aan touch de 'geslotenk kringloop', toen weer (gesluitend op gemeen:\nniveau).\n\nDe term 'gestolen kringloop' wordt gebruikt om een situatie te beschrijvehyeen informatie wordt gebruikt\nter controle van hetgeen er met metten 'gebeurt'of om een corrigerend(er) verbererding op gang te\nbrengen - een 'gecomoliceerd proces' in tegenstelling tot een ongecomt roleerd proces.",
  "kernconcepten": [
    "PDCA-model",
    "Demingwiele",
    "ISO 27001 procesmodel",
    "gesloten kringloop",
    "continue verbetering",
    "TQM",
    "Kaizen",
    "DMAIC"
  ],
  "_source": "Foto 18-04-2026, 18 37 27.jpg",
  "_input_tokens": 1897,
  "_output_tokens": 374
}